velt_py/__init__.py
velt_py/config.py
velt_py/exceptions.py
velt_py/sdk.py
velt_py/backends/__init__.py
velt_py/backends/self_hosting_backend.py
velt_py/database/__init__.py
velt_py/database/base.py
velt_py/database/connection.py
velt_py/database/mongodb_adapter.py
velt_py/models/__init__.py
velt_py/models/attachment.py
velt_py/models/base.py
velt_py/models/comment.py
velt_py/models/enums.py
velt_py/models/reaction.py
velt_py/models/user.py
velt_py/services/__init__.py
velt_py/services/api/__init__.py
velt_py/services/api/token_service.py
velt_py/services/self_hosting/__init__.py
velt_py/services/self_hosting/attachment_service.py
velt_py/services/self_hosting/base_service.py
velt_py/services/self_hosting/comment_service.py
velt_py/services/self_hosting/reaction_service.py
velt_py/services/self_hosting/user_service.py
velt_py/services/storage/__init__.py
velt_py/services/storage/s3_service.py
velt_py-0.1.5.dist-info/licenses/LICENSE
velt_py-0.1.5.dist-info/METADATA
velt_py-0.1.5.dist-info/WHEEL
velt_py-0.1.5.dist-info/top_level.txt
velt_py-0.1.5.dist-info/RECORD
