Metadata-Version: 2.4
Name: velt-py
Version: 0.1.5
Summary: Python SDK for integrating Velt comments, reactions, attachments, and user management into Django applications
Home-page: https://github.com/snippyly/velt-py-sdk
Author: Velt
Author-email: Velt <support@velt.dev>
License: MIT
Project-URL: Homepage, https://github.com/snippyly/velt-py-sdk
Project-URL: Repository, https://github.com/snippyly/velt-py-sdk
Keywords: velt,comments,collaboration,django,mongodb
Classifier: Development Status :: 4 - Beta
Classifier: Intended Audience :: Developers
Classifier: License :: OSI Approved :: MIT License
Classifier: Programming Language :: Python :: 3
Classifier: Programming Language :: Python :: 3.8
Classifier: Programming Language :: Python :: 3.9
Classifier: Programming Language :: Python :: 3.10
Classifier: Programming Language :: Python :: 3.11
Classifier: Programming Language :: Python :: 3.12
Classifier: Framework :: Django
Requires-Python: >=3.8
License-File: LICENSE
Requires-Dist: pymongo[srv,tls]==4.6.3
Requires-Dist: mongoengine==0.27.0
Requires-Dist: blinker==1.8.2
Requires-Dist: python-dateutil==2.8.2
Requires-Dist: requests>=2.25.0
Requires-Dist: boto3>=1.28.0
Provides-Extra: dev
Requires-Dist: pytest>=7.0.0; extra == "dev"
Requires-Dist: pytest-cov>=4.0.0; extra == "dev"
Requires-Dist: mongomock>=4.1.2; extra == "dev"
Requires-Dist: responses>=0.23.0; extra == "dev"
Dynamic: author
Dynamic: home-page
Dynamic: license-file
Dynamic: requires-python
